sns_sqs_services/__init__.py
sns_sqs_services/services.py
django_sns_sqs_services-0.1.3.dist-info/LICENSE
django_sns_sqs_services-0.1.3.dist-info/METADATA
django_sns_sqs_services-0.1.3.dist-info/WHEEL
django_sns_sqs_services-0.1.3.dist-info/top_level.txt
django_sns_sqs_services-0.1.3.dist-info/RECORD
