Metadata-Version: 2.1
Name: django-sns-sqs-services
Version: 0.1.3
Summary: Helpers functions for send sqs and sns aws messages
Home-page: https://bitbucket.org/ctroc/django-sns-sqs-services/src/master/
Author: Yaeko Ogino & Christopher Troc
Author-email: christopher.troc@cumplo.com
License: MIT
Keywords: django sqs sns helpers
Platform: UNKNOWN
Classifier: Development Status :: 4 - Beta
Classifier: Environment :: Web Environment
Classifier: Framework :: Django :: 1.11
Classifier: Intended Audience :: Developers
Classifier: License :: OSI Approved :: MIT License
Classifier: Natural Language :: Spanish
Classifier: Operating System :: Unix
Classifier: Programming Language :: Python
Classifier: Programming Language :: Python :: 3
Classifier: Programming Language :: Python :: 3.7
Requires-Dist: django
Requires-Dist: django-rest-framework
Requires-Dist: boto3
